tap_canvas_blank/__init__.py
tap_canvas_blank/cli.py
tap_canvas_blank/client.py
tap_canvas_blank/streams.py
tap_canvas_blank/tap.py
tap_canvas_blank/tests/__init__.py
tap_canvas_blank/tests/test_core.py
tap_canvas_blank/typing.py
tap_canvas_blank-0.0.5.dist-info/entry_points.txt
tap_canvas_blank-0.0.5.dist-info/METADATA
tap_canvas_blank-0.0.5.dist-info/WHEEL
tap_canvas_blank-0.0.5.dist-info/RECORD
