Metadata-Version: 2.1
Name: tap-canvas-blank
Version: 0.0.5
Summary: Singer tap for Canvas, built with the Meltano SDK for Singer Taps.
License: Apache 2.0
Keywords: ELT,canvas
Author: Bruno Arnabar
Requires-Python: >=3.8,<4
Classifier: License :: Other/Proprietary License
Classifier: Programming Language :: Python :: 3
Classifier: Programming Language :: Python :: 3.8
Classifier: Programming Language :: Python :: 3.9
Classifier: Programming Language :: Python :: 3.10
Classifier: Programming Language :: Python :: 3.11
Classifier: Programming Language :: Python :: 3.12
Classifier: Programming Language :: Python :: 3.13
Requires-Dist: memoization (>=0.4,<0.5)
Requires-Dist: requests (>=2.25.1,<3.0.0)
Requires-Dist: singer-sdk (>=0.3.12)
